{
  "kind": "youtube#searchListResponse",
  "etag": "R2Te56Ulnq5pdq2HGfetann72yI",
  "nextPageToken": "CDIQAA",
  "regionCode": "CZ",
  "pageInfo": {
    "totalResults": 1216,
    "resultsPerPage": 50
  },
  "items": [
    {
      "kind": "youtube#searchResult",
      "etag": "dqVO6SXU8QrW3DwuG7sFVXlDJcQ",
      "id": {
        "kind": "youtube#video",
        "videoId": "TP6XTSnuk5s"
      },
      "snippet": {
        "publishedAt": "2023-04-10T14:00:26Z",
        "channelId": "UCLsooMJoIpl_7ux2jvdPB-Q",
        "title": "Peekaboo Playground #shorts #kidssongs #supersimplesongs",
        "description": "Get the Super Simple App! ▻ http://bit.ly/TheSuperSimpleApp Peekaboo is hiding in the playground! Can you find Peekaboo Cat?",
        "thumbnails": {
          "default": {
            "url": "https://i.ytimg.com/vi/TP6XTSnuk5s/default.jpg",
            "width": 120,
            "height": 90
          },
          "medium": {
            "url": "https://i.ytimg.com/vi/TP6XTSnuk5s/mqdefault.jpg",
            "width": 320,
            "height": 180
          },
          "high": {
            "url": "https://i.ytimg.com/vi/TP6XTSnuk5s/hqdefault.jpg",
            "width": 480,
            "height": 360
          }
        },
        "channelTitle": "Super Simple Songs - Kids Songs",
        "liveBroadcastContent": "none",
        "publishTime": "2023-04-10T14:00:26Z"
      }
    },
    {
      "kind": "youtube#searchResult",
      "etag": "l8KC41lToicV6vrJ6_au1N38qK4",
      "id": {
        "kind": "youtube#video",
        "videoId": "Zxl_DJjBeVI"
      },
      "snippet": {
        "publishedAt": "2023-04-08T14:00:24Z",
        "channelId": "UCLsooMJoIpl_7ux2jvdPB-Q",
        "title": "Hello Hello! #shorts #kidssongs #supersimplesongs",
        "description": "Get the Super Simple App! ▻ http://bit.ly/TheSuperSimpleApp Hello, hello. Can you clap your hands? Hello, hello. Can you ...",
        "thumbnails": {
          "default": {
            "url": "https://i.ytimg.com/vi/Zxl_DJjBeVI/default.jpg",
            "width": 120,
            "height": 90
          },
          "medium": {
            "url": "https://i.ytimg.com/vi/Zxl_DJjBeVI/mqdefault.jpg",
            "width": 320,
            "height": 180
          },
          "high": {
            "url": "https://i.ytimg.com/vi/Zxl_DJjBeVI/hqdefault.jpg",
            "width": 480,
            "height": 360
          }
        },
        "channelTitle": "Super Simple Songs - Kids Songs",
        "liveBroadcastContent": "none",
        "publishTime": "2023-04-08T14:00:24Z"
      }
    },
    {
      "kind": "youtube#searchResult",
      "etag": "I0le5DJSpLlljF_oi_VY7nAcQR0",
      "id": {
        "kind": "youtube#video",
        "videoId": "Lxd64ix4sG4"
      },
      "snippet": {
        "publishedAt": "2023-04-06T14:00:12Z",
        "channelId": "UCLsooMJoIpl_7ux2jvdPB-Q",
        "title": "Raindrops Falling💧| Kids Songs | Super Simple Songs",
        "description": "Get the Super Simple App! ▻ http://bit.ly/TheSuperSimpleApp Baby Bear and Bunny are discovering rain together. This is the ...",
        "thumbnails": {
          "default": {
            "url": "https://i.ytimg.com/vi/Lxd64ix4sG4/default.jpg",
            "width": 120,
            "height": 90
          },
          "medium": {
            "url": "https://i.ytimg.com/vi/Lxd64ix4sG4/mqdefault.jpg",
            "width": 320,
            "height": 180
          },
          "high": {
            "url": "https://i.ytimg.com/vi/Lxd64ix4sG4/hqdefault.jpg",
            "width": 480,
            "height": 360
          }
        },
        "channelTitle": "Super Simple Songs - Kids Songs",
        "liveBroadcastContent": "none",
        "publishTime": "2023-04-06T14:00:12Z"
      }
    },
    {
      "kind": "youtube#searchResult",
      "etag": "zgVizF93Pwyjs0gZh-tkgXXGThw",
      "id": {
        "kind": "youtube#video",
        "videoId": "sUHNa0hCt7E"
      },
      "snippet": {
        "publishedAt": "2023-04-06T13:43:02Z",
        "channelId": "UCLsooMJoIpl_7ux2jvdPB-Q",
        "title": "🔴  Super Simple Songs Bedtime Livestream 🌟🦉💤 | Kids Nap Songs | Super Simple Songs",
        "description": "Get the Super Simple App! ▻ http://bit.ly/TheSuperSimpleApp PARENTS AND TEACHERS: Thank you so much for watching ...",
        "thumbnails": {
          "default": {
            "url": "https://i.ytimg.com/vi/sUHNa0hCt7E/default_live.jpg",
            "width": 120,
            "height": 90
          },
          "medium": {
            "url": "https://i.ytimg.com/vi/sUHNa0hCt7E/mqdefault_live.jpg",
            "width": 320,
            "height": 180
          },
          "high": {
            "url": "https://i.ytimg.com/vi/sUHNa0hCt7E/hqdefault_live.jpg",
            "width": 480,
            "height": 360
          }
        },
        "channelTitle": "Super Simple Songs - Kids Songs",
        "liveBroadcastContent": "live",
        "publishTime": "2023-04-06T13:43:02Z"
      }
    },
    {
      "kind": "youtube#searchResult",
      "etag": "o6nInffsDN1dZ_gpSW_GD_hpEU0",
      "id": {
        "kind": "youtube#video",
        "videoId": "qO8QK0P7sDc"
      },
      "snippet": {
        "publishedAt": "2023-04-06T13:40:22Z",
        "channelId": "UCLsooMJoIpl_7ux2jvdPB-Q",
        "title": "🔴 Finny The Shark Livestream 🦈 🐙🐠 | Kids Songs | Super Simple Songs",
        "description": "Get the Super Simple App! ▻ http://bit.ly/TheSuperSimpleApp PARENTS AND TEACHERS: Thank you so much for watching ...",
        "thumbnails": {
          "default": {
            "url": "https://i.ytimg.com/vi/qO8QK0P7sDc/default_live.jpg",
            "width": 120,
            "height": 90
          },
          "medium": {
            "url": "https://i.ytimg.com/vi/qO8QK0P7sDc/mqdefault_live.jpg",
            "width": 320,
            "height": 180
          },
          "high": {
            "url": "https://i.ytimg.com/vi/qO8QK0P7sDc/hqdefault_live.jpg",
            "width": 480,
            "height": 360
          }
        },
        "channelTitle": "Super Simple Songs - Kids Songs",
        "liveBroadcastContent": "live",
        "publishTime": "2023-04-06T13:40:22Z"
      }
    },
    {
      "kind": "youtube#searchResult",
      "etag": "ENOPAA7IaVBPwem10N-QDacFBw8",
      "id": {
        "kind": "youtube#video",
        "videoId": "M8tsPj_1bns"
      },
      "snippet": {
        "publishedAt": "2023-04-06T13:38:11Z",
        "channelId": "UCLsooMJoIpl_7ux2jvdPB-Q",
        "title": "🔴 Super Simple Songs LIVE 🎶 | Kids Songs | Super Simple Songs",
        "description": "Get the Super Simple App! ▻ http://bit.ly/TheSuperSimpleApp PARENTS AND TEACHERS: Thank you so much for watching ...",
        "thumbnails": {
          "default": {
            "url": "https://i.ytimg.com/vi/M8tsPj_1bns/default_live.jpg",
            "width": 120,
            "height": 90
          },
          "medium": {
            "url": "https://i.ytimg.com/vi/M8tsPj_1bns/mqdefault_live.jpg",
            "width": 320,
            "height": 180
          },
          "high": {
            "url": "https://i.ytimg.com/vi/M8tsPj_1bns/hqdefault_live.jpg",
            "width": 480,
            "height": 360
          }
        },
        "channelTitle": "Super Simple Songs - Kids Songs",
        "liveBroadcastContent": "live",
        "publishTime": "2023-04-06T13:38:11Z"
      }
    },
    {
      "kind": "youtube#searchResult",
      "etag": "aBYY4PPlKdRqaMhYp0_0v-xJV9k",
      "id": {
        "kind": "youtube#video",
        "videoId": "cusyp6ys-Wg"
      },
      "snippet": {
        "publishedAt": "2023-04-05T14:00:31Z",
        "channelId": "UCLsooMJoIpl_7ux2jvdPB-Q",
        "title": "Fork Flowers For Spring! #kidscrafts #supersimplecrafts #shorts",
        "description": "Get the Super Simple App! ▻ http://bit.ly/TheSuperSimpleApp These fork flowers are super fun to stamp! We hope you enjoy ...",
        "thumbnails": {
          "default": {
            "url": "https://i.ytimg.com/vi/cusyp6ys-Wg/default.jpg",
            "width": 120,
            "height": 90
          },
          "medium": {
            "url": "https://i.ytimg.com/vi/cusyp6ys-Wg/mqdefault.jpg",
            "width": 320,
            "height": 180
          },
          "high": {
            "url": "https://i.ytimg.com/vi/cusyp6ys-Wg/hqdefault.jpg",
            "width": 480,
            "height": 360
          }
        },
        "channelTitle": "Super Simple Songs - Kids Songs",
        "liveBroadcastContent": "none",
        "publishTime": "2023-04-05T14:00:31Z"
      }
    },
    {
      "kind": "youtube#searchResult",
      "etag": "OetKKkRnEaLd6SqxJCRYb0Wp8mM",
      "id": {
        "kind": "youtube#video",
        "videoId": "LzMdmivzDtk"
      },
      "snippet": {
        "publishedAt": "2023-04-03T14:00:19Z",
        "channelId": "UCLsooMJoIpl_7ux2jvdPB-Q",
        "title": "Butterfly Ladybug Bumblebee 🦋🐞🐝 #shorts #supersimplesongs #kidssongs",
        "description": "Get the Super Simple App! ▻ http://bit.ly/TheSuperSimpleApp Sing along to this sweet spring song! ▻ WATCH NOW ...",
        "thumbnails": {
          "default": {
            "url": "https://i.ytimg.com/vi/LzMdmivzDtk/default.jpg",
            "width": 120,
            "height": 90
          },
          "medium": {
            "url": "https://i.ytimg.com/vi/LzMdmivzDtk/mqdefault.jpg",
            "width": 320,
            "height": 180
          },
          "high": {
            "url": "https://i.ytimg.com/vi/LzMdmivzDtk/hqdefault.jpg",
            "width": 480,
            "height": 360
          }
        },
        "channelTitle": "Super Simple Songs - Kids Songs",
        "liveBroadcastContent": "none",
        "publishTime": "2023-04-03T14:00:19Z"
      }
    },
    {
      "kind": "youtube#searchResult",
      "etag": "T3McYJslu2836nMwHoRLXpiMwKw",
      "id": {
        "kind": "youtube#video",
        "videoId": "LciUMOjRj7Y"
      },
      "snippet": {
        "publishedAt": "2023-04-01T14:00:24Z",
        "channelId": "UCLsooMJoIpl_7ux2jvdPB-Q",
        "title": "Take Me Out To The Ball Game ⚾️ #takemeouttotheballgame #shorts #supersimplesongs",
        "description": "Get the Super Simple App! ▻ http://bit.ly/TheSuperSimpleApp It's officially baseball season! Let's GO!!! ▻ WATCH NOW ...",
        "thumbnails": {
          "default": {
            "url": "https://i.ytimg.com/vi/LciUMOjRj7Y/default.jpg",
            "width": 120,
            "height": 90
          },
          "medium": {
            "url": "https://i.ytimg.com/vi/LciUMOjRj7Y/mqdefault.jpg",
            "width": 320,
            "height": 180
          },
          "high": {
            "url": "https://i.ytimg.com/vi/LciUMOjRj7Y/hqdefault.jpg",
            "width": 480,
            "height": 360
          }
        },
        "channelTitle": "Super Simple Songs - Kids Songs",
        "liveBroadcastContent": "none",
        "publishTime": "2023-04-01T14:00:24Z"
      }
    },
    {
      "kind": "youtube#searchResult",
      "etag": "VJOP_WLt-iw8jTpuxN4SF49OFcg",
      "id": {
        "kind": "youtube#video",
        "videoId": "YaV4Zq0kLQU"
      },
      "snippet": {
        "publishedAt": "2023-03-30T14:00:17Z",
        "channelId": "UCLsooMJoIpl_7ux2jvdPB-Q",
        "title": "Animal Songs For Kids! | Earth Month Celebration | Super Simple Songs",
        "description": "Get the Super Simple App! ▻ http://bit.ly/TheSuperSimpleApp It's Earth Month and we're celebrating with animal songs! Name the ...",
        "thumbnails": {
          "default": {
            "url": "https://i.ytimg.com/vi/YaV4Zq0kLQU/default.jpg",
            "width": 120,
            "height": 90
          },
          "medium": {
            "url": "https://i.ytimg.com/vi/YaV4Zq0kLQU/mqdefault.jpg",
            "width": 320,
            "height": 180
          },
          "high": {
            "url": "https://i.ytimg.com/vi/YaV4Zq0kLQU/hqdefault.jpg",
            "width": 480,
            "height": 360
          }
        },
        "channelTitle": "Super Simple Songs - Kids Songs",
        "liveBroadcastContent": "none",
        "publishTime": "2023-03-30T14:00:17Z"
      }
    },
    {
      "kind": "youtube#searchResult",
      "etag": "lQfaG5dKKgQM5Fd4SiBapJhE4aI",
      "id": {
        "kind": "youtube#video",
        "videoId": "QVQUr03aCyQ"
      },
      "snippet": {
        "publishedAt": "2023-03-29T14:00:17Z",
        "channelId": "UCLsooMJoIpl_7ux2jvdPB-Q",
        "title": "Baseball Name Plate Craft #supersimplecrafts #shorts #baseballcraft",
        "description": "Get the Super Simple App! ▻ http://bit.ly/TheSuperSimpleApp Are you ready for MLB 2023? Let's make a cool craft to celebrate ...",
        "thumbnails": {
          "default": {
            "url": "https://i.ytimg.com/vi/QVQUr03aCyQ/default.jpg",
            "width": 120,
            "height": 90
          },
          "medium": {
            "url": "https://i.ytimg.com/vi/QVQUr03aCyQ/mqdefault.jpg",
            "width": 320,
            "height": 180
          },
          "high": {
            "url": "https://i.ytimg.com/vi/QVQUr03aCyQ/hqdefault.jpg",
            "width": 480,
            "height": 360
          }
        },
        "channelTitle": "Super Simple Songs - Kids Songs",
        "liveBroadcastContent": "none",
        "publishTime": "2023-03-29T14:00:17Z"
      }
    },
    {
      "kind": "youtube#searchResult",
      "etag": "ItEBgwSM3nICHtMpbiOnGqkVWcY",
      "id": {
        "kind": "youtube#video",
        "videoId": "rh6p7lI93xs"
      },
      "snippet": {
        "publishedAt": "2023-03-27T14:00:28Z",
        "channelId": "UCLsooMJoIpl_7ux2jvdPB-Q",
        "title": "If You&#39;re Happy And You Know It Spin Around #shorts #preschool #kidssongs #supersimplesongs",
        "description": "Get the Super Simple App! ▻ http://bit.ly/TheSuperSimpleApp Spin around and touch the ground with Noodle & Pals! ▻ WATCH ...",
        "thumbnails": {
          "default": {
            "url": "https://i.ytimg.com/vi/rh6p7lI93xs/default.jpg",
            "width": 120,
            "height": 90
          },
          "medium": {
            "url": "https://i.ytimg.com/vi/rh6p7lI93xs/mqdefault.jpg",
            "width": 320,
            "height": 180
          },
          "high": {
            "url": "https://i.ytimg.com/vi/rh6p7lI93xs/hqdefault.jpg",
            "width": 480,
            "height": 360
          }
        },
        "channelTitle": "Super Simple Songs - Kids Songs",
        "liveBroadcastContent": "none",
        "publishTime": "2023-03-27T14:00:28Z"
      }
    },
    {
      "kind": "youtube#searchResult",
      "etag": "wTW1quw9KvIxbRsBIshH6vzs5iw",
      "id": {
        "kind": "youtube#video",
        "videoId": "9SATf5vDf4M"
      },
      "snippet": {
        "publishedAt": "2023-03-20T14:00:05Z",
        "channelId": "UCLsooMJoIpl_7ux2jvdPB-Q",
        "title": "The Itsy Bitsy Spider | Kids Songs | Super Simple Songs",
        "description": "Get the Super Simple App! ▻ http://bit.ly/TheSuperSimpleApp Sing along to The Itsy Bitsy Spider! Can you use your hand ...",
        "thumbnails": {
          "default": {
            "url": "https://i.ytimg.com/vi/9SATf5vDf4M/default.jpg",
            "width": 120,
            "height": 90
          },
          "medium": {
            "url": "https://i.ytimg.com/vi/9SATf5vDf4M/mqdefault.jpg",
            "width": 320,
            "height": 180
          },
          "high": {
            "url": "https://i.ytimg.com/vi/9SATf5vDf4M/hqdefault.jpg",
            "width": 480,
            "height": 360
          }
        },
        "channelTitle": "Super Simple Songs - Kids Songs",
        "liveBroadcastContent": "none",
        "publishTime": "2023-03-20T14:00:05Z"
      }
    },
    {
      "kind": "youtube#searchResult",
      "etag": "SOm-RehdOkttgPvHXb56Ce9Sn8o",
      "id": {
        "kind": "youtube#video",
        "videoId": "S9yh26O8Z6w"
      },
      "snippet": {
        "publishedAt": "2023-03-16T14:00:18Z",
        "channelId": "UCLsooMJoIpl_7ux2jvdPB-Q",
        "title": "The Hand Washing Song And More | Children&#39;s Music | Super Simple Songs",
        "description": "Get the Super Simple App! ▻ http://bit.ly/TheSuperSimpleApp Practice hand washing skills with Noodle & Pals and sing along to ...",
        "thumbnails": {
          "default": {
            "url": "https://i.ytimg.com/vi/S9yh26O8Z6w/default.jpg",
            "width": 120,
            "height": 90
          },
          "medium": {
            "url": "https://i.ytimg.com/vi/S9yh26O8Z6w/mqdefault.jpg",
            "width": 320,
            "height": 180
          },
          "high": {
            "url": "https://i.ytimg.com/vi/S9yh26O8Z6w/hqdefault.jpg",
            "width": 480,
            "height": 360
          }
        },
        "channelTitle": "Super Simple Songs - Kids Songs",
        "liveBroadcastContent": "none",
        "publishTime": "2023-03-16T14:00:18Z"
      }
    },
    {
      "kind": "youtube#searchResult",
      "etag": "xRxot7IgtiXMdAbPcR5SDra9lw0",
      "id": {
        "kind": "youtube#video",
        "videoId": "-88_sHRaCaE"
      },
      "snippet": {
        "publishedAt": "2023-03-15T14:00:00Z",
        "channelId": "UCLsooMJoIpl_7ux2jvdPB-Q",
        "title": "Sock Puppets #shorts #kidscrafts #supersimplecrafts",
        "description": "Get the Super Simple App! ▻ http://bit.ly/TheSuperSimpleApp Let's make some cool sock puppets for #craftywednesday.",
        "thumbnails": {
          "default": {
            "url": "https://i.ytimg.com/vi/-88_sHRaCaE/default.jpg",
            "width": 120,
            "height": 90
          },
          "medium": {
            "url": "https://i.ytimg.com/vi/-88_sHRaCaE/mqdefault.jpg",
            "width": 320,
            "height": 180
          },
          "high": {
            "url": "https://i.ytimg.com/vi/-88_sHRaCaE/hqdefault.jpg",
            "width": 480,
            "height": 360
          }
        },
        "channelTitle": "Super Simple Songs - Kids Songs",
        "liveBroadcastContent": "none",
        "publishTime": "2023-03-15T14:00:00Z"
      }
    },
    {
      "kind": "youtube#searchResult",
      "etag": "TibkwOSUXBUs7I4s5SPuM_q-b0M",
      "id": {
        "kind": "youtube#video",
        "videoId": "gOYXR_TYlEg"
      },
      "snippet": {
        "publishedAt": "2023-03-13T14:00:21Z",
        "channelId": "UCLsooMJoIpl_7ux2jvdPB-Q",
        "title": "Over The Deep Blue Sea #shorts #kidssongs #supersimplesongs",
        "description": "Get the Super Simple App! ▻ http://bit.ly/TheSuperSimpleApp Climb aboard and be a pirate for the day! Yarrrrr! ⚓️ ▻ WATCH ...",
        "thumbnails": {
          "default": {
            "url": "https://i.ytimg.com/vi/gOYXR_TYlEg/default.jpg",
            "width": 120,
            "height": 90
          },
          "medium": {
            "url": "https://i.ytimg.com/vi/gOYXR_TYlEg/mqdefault.jpg",
            "width": 320,
            "height": 180
          },
          "high": {
            "url": "https://i.ytimg.com/vi/gOYXR_TYlEg/hqdefault.jpg",
            "width": 480,
            "height": 360
          }
        },
        "channelTitle": "Super Simple Songs - Kids Songs",
        "liveBroadcastContent": "none",
        "publishTime": "2023-03-13T14:00:21Z"
      }
    },
    {
      "kind": "youtube#searchResult",
      "etag": "OAU4pFFPXETfX7tlppIA2UJs5ZY",
      "id": {
        "kind": "youtube#video",
        "videoId": "ZHtt0ipdGoo"
      },
      "snippet": {
        "publishedAt": "2023-03-11T15:00:18Z",
        "channelId": "UCLsooMJoIpl_7ux2jvdPB-Q",
        "title": "The Rainbow Song 🌈 #shorts #kidssongs #supersimplesongs",
        "description": "Get the Super Simple App! ▻ http://bit.ly/TheSuperSimpleApp Do you know all of the colors in the rainbow? Let's sing about them!",
        "thumbnails": {
          "default": {
            "url": "https://i.ytimg.com/vi/ZHtt0ipdGoo/default.jpg",
            "width": 120,
            "height": 90
          },
          "medium": {
            "url": "https://i.ytimg.com/vi/ZHtt0ipdGoo/mqdefault.jpg",
            "width": 320,
            "height": 180
          },
          "high": {
            "url": "https://i.ytimg.com/vi/ZHtt0ipdGoo/hqdefault.jpg",
            "width": 480,
            "height": 360
          }
        },
        "channelTitle": "Super Simple Songs - Kids Songs",
        "liveBroadcastContent": "none",
        "publishTime": "2023-03-11T15:00:18Z"
      }
    },
    {
      "kind": "youtube#searchResult",
      "etag": "rFhSDW-bYcV0a226c1MIgqY5Hqo",
      "id": {
        "kind": "youtube#video",
        "videoId": "DspTKxy0Cf0"
      },
      "snippet": {
        "publishedAt": "2023-03-04T15:00:09Z",
        "channelId": "UCLsooMJoIpl_7ux2jvdPB-Q",
        "title": "BINGO! #shorts #kidssongs #supersimplesongs",
        "description": "Get the Super Simple App! ▻ http://bit.ly/TheSuperSimpleApp We added some actions to this super fun kids song! There was a ...",
        "thumbnails": {
          "default": {
            "url": "https://i.ytimg.com/vi/DspTKxy0Cf0/default.jpg",
            "width": 120,
            "height": 90
          },
          "medium": {
            "url": "https://i.ytimg.com/vi/DspTKxy0Cf0/mqdefault.jpg",
            "width": 320,
            "height": 180
          },
          "high": {
            "url": "https://i.ytimg.com/vi/DspTKxy0Cf0/hqdefault.jpg",
            "width": 480,
            "height": 360
          }
        },
        "channelTitle": "Super Simple Songs - Kids Songs",
        "liveBroadcastContent": "none",
        "publishTime": "2023-03-04T15:00:09Z"
      }
    },
    {
      "kind": "youtube#searchResult",
      "etag": "LE54ymBU5FRE_GW3lfioWeLVoCI",
      "id": {
        "kind": "youtube#video",
        "videoId": "e0ol5NQrHds"
      },
      "snippet": {
        "publishedAt": "2023-03-01T15:00:33Z",
        "channelId": "UCLsooMJoIpl_7ux2jvdPB-Q",
        "title": "Rain Cloud Craft #kidscrafts #shorts #supersimplecrafts",
        "description": "Get the Super Simple App! ▻ http://bit.ly/TheSuperSimpleApp It's so fun to melt crayons and make some rain!",
        "thumbnails": {
          "default": {
            "url": "https://i.ytimg.com/vi/e0ol5NQrHds/default.jpg",
            "width": 120,
            "height": 90
          },
          "medium": {
            "url": "https://i.ytimg.com/vi/e0ol5NQrHds/mqdefault.jpg",
            "width": 320,
            "height": 180
          },
          "high": {
            "url": "https://i.ytimg.com/vi/e0ol5NQrHds/hqdefault.jpg",
            "width": 480,
            "height": 360
          }
        },
        "channelTitle": "Super Simple Songs - Kids Songs",
        "liveBroadcastContent": "none",
        "publishTime": "2023-03-01T15:00:33Z"
      }
    },
    {
      "kind": "youtube#searchResult",
      "etag": "DwX4fBHO8gv5deUkjegQDABsh70",
      "id": {
        "kind": "youtube#video",
        "videoId": "dPzfHWXGUes"
      },
      "snippet": {
        "publishedAt": "2023-02-22T15:00:23Z",
        "channelId": "UCLsooMJoIpl_7ux2jvdPB-Q",
        "title": "DIY Pretend Play Pasta #diycrafts #supersimplecrafts #shorts",
        "description": "Get the Super Simple App! ▻ http://bit.ly/TheSuperSimpleApp Fun with felt! Make some super fun play food: pasta and meatballs!",
        "thumbnails": {
          "default": {
            "url": "https://i.ytimg.com/vi/dPzfHWXGUes/default.jpg",
            "width": 120,
            "height": 90
          },
          "medium": {
            "url": "https://i.ytimg.com/vi/dPzfHWXGUes/mqdefault.jpg",
            "width": 320,
            "height": 180
          },
          "high": {
            "url": "https://i.ytimg.com/vi/dPzfHWXGUes/hqdefault.jpg",
            "width": 480,
            "height": 360
          }
        },
        "channelTitle": "Super Simple Songs - Kids Songs",
        "liveBroadcastContent": "none",
        "publishTime": "2023-02-22T15:00:23Z"
      }
    },
    {
      "kind": "youtube#searchResult",
      "etag": "_UJgd0cmCXaSahE9PjHSeJF4-lc",
      "id": {
        "kind": "youtube#video",
        "videoId": "xEeRB4j-MgE"
      },
      "snippet": {
        "publishedAt": "2023-02-20T15:00:44Z",
        "channelId": "UCLsooMJoIpl_7ux2jvdPB-Q",
        "title": "Are You Sleeping, Baby Bear? #shorts #kidssongs #supersimplesongs",
        "description": "Get the Super Simple App! ▻ http://bit.ly/TheSuperSimpleApp Bunny wants Baby Bear to get up and play! The morning sun is ...",
        "thumbnails": {
          "default": {
            "url": "https://i.ytimg.com/vi/xEeRB4j-MgE/default.jpg",
            "width": 120,
            "height": 90
          },
          "medium": {
            "url": "https://i.ytimg.com/vi/xEeRB4j-MgE/mqdefault.jpg",
            "width": 320,
            "height": 180
          },
          "high": {
            "url": "https://i.ytimg.com/vi/xEeRB4j-MgE/hqdefault.jpg",
            "width": 480,
            "height": 360
          }
        },
        "channelTitle": "Super Simple Songs - Kids Songs",
        "liveBroadcastContent": "none",
        "publishTime": "2023-02-20T15:00:44Z"
      }
    },
    {
      "kind": "youtube#searchResult",
      "etag": "3lO1u2aDEM2IuG1ag0H2PmzsqU4",
      "id": {
        "kind": "youtube#video",
        "videoId": "MaAsdbz-W88"
      },
      "snippet": {
        "publishedAt": "2023-02-15T15:00:11Z",
        "channelId": "UCLsooMJoIpl_7ux2jvdPB-Q",
        "title": "Rainbow Heart Craft 🌈 ❤️ #shorts #kidscrafts #supersimplecrafts",
        "description": "Get the Super Simple App! ▻ http://bit.ly/TheSuperSimpleApp It's #craftywednesday! Make a rainbow heart with these super fun ...",
        "thumbnails": {
          "default": {
            "url": "https://i.ytimg.com/vi/MaAsdbz-W88/default.jpg",
            "width": 120,
            "height": 90
          },
          "medium": {
            "url": "https://i.ytimg.com/vi/MaAsdbz-W88/mqdefault.jpg",
            "width": 320,
            "height": 180
          },
          "high": {
            "url": "https://i.ytimg.com/vi/MaAsdbz-W88/hqdefault.jpg",
            "width": 480,
            "height": 360
          }
        },
        "channelTitle": "Super Simple Songs - Kids Songs",
        "liveBroadcastContent": "none",
        "publishTime": "2023-02-15T15:00:11Z"
      }
    },
    {
      "kind": "youtube#searchResult",
      "etag": "A_5_0BqAUZbeJenXTy_W7BRS8sU",
      "id": {
        "kind": "youtube#video",
        "videoId": "oAGpauAhvwo"
      },
      "snippet": {
        "publishedAt": "2023-02-11T15:00:28Z",
        "channelId": "UCLsooMJoIpl_7ux2jvdPB-Q",
        "title": "Five Little Chicks  #shorts #kidssongs #lullaby",
        "description": "Get the Super Simple App! ▻ http://bit.ly/TheSuperSimpleApp Count down from five with these sleepy chicks. Five little ...",
        "thumbnails": {
          "default": {
            "url": "https://i.ytimg.com/vi/oAGpauAhvwo/default.jpg",
            "width": 120,
            "height": 90
          },
          "medium": {
            "url": "https://i.ytimg.com/vi/oAGpauAhvwo/mqdefault.jpg",
            "width": 320,
            "height": 180
          },
          "high": {
            "url": "https://i.ytimg.com/vi/oAGpauAhvwo/hqdefault.jpg",
            "width": 480,
            "height": 360
          }
        },
        "channelTitle": "Super Simple Songs - Kids Songs",
        "liveBroadcastContent": "none",
        "publishTime": "2023-02-11T15:00:28Z"
      }
    },
    {
      "kind": "youtube#searchResult",
      "etag": "mV1aqadIDqVeHWQPsXo1aniv2Rg",
      "id": {
        "kind": "youtube#video",
        "videoId": "2HZajbnuP7w"
      },
      "snippet": {
        "publishedAt": "2023-02-08T15:00:01Z",
        "channelId": "UCLsooMJoIpl_7ux2jvdPB-Q",
        "title": "Super Simple Valentine&#39;s Day Cards ❤️ #shorts #kidscrafts #supersimplecrafts",
        "description": "Get the Super Simple App! ▻ http://bit.ly/TheSuperSimpleApp Make some super sweet Super Simple valentine cards for your ...",
        "thumbnails": {
          "default": {
            "url": "https://i.ytimg.com/vi/2HZajbnuP7w/default.jpg",
            "width": 120,
            "height": 90
          },
          "medium": {
            "url": "https://i.ytimg.com/vi/2HZajbnuP7w/mqdefault.jpg",
            "width": 320,
            "height": 180
          },
          "high": {
            "url": "https://i.ytimg.com/vi/2HZajbnuP7w/hqdefault.jpg",
            "width": 480,
            "height": 360
          }
        },
        "channelTitle": "Super Simple Songs - Kids Songs",
        "liveBroadcastContent": "none",
        "publishTime": "2023-02-08T15:00:01Z"
      }
    },
    {
      "kind": "youtube#searchResult",
      "etag": "RYbNwRqTiDNb5Nczs2sPAJZvUxU",
      "id": {
        "kind": "youtube#video",
        "videoId": "fTk3ucrjuIc"
      },
      "snippet": {
        "publishedAt": "2023-02-06T15:00:20Z",
        "channelId": "UCLsooMJoIpl_7ux2jvdPB-Q",
        "title": "I Have A Pet #shorts #kidssongs #supersimplesongs #pets",
        "description": "Get the Super Simple App! ▻ http://bit.ly/TheSuperSimpleApp Do you have a pet? Add your pet to this super fun song for ...",
        "thumbnails": {
          "default": {
            "url": "https://i.ytimg.com/vi/fTk3ucrjuIc/default.jpg",
            "width": 120,
            "height": 90
          },
          "medium": {
            "url": "https://i.ytimg.com/vi/fTk3ucrjuIc/mqdefault.jpg",
            "width": 320,
            "height": 180
          },
          "high": {
            "url": "https://i.ytimg.com/vi/fTk3ucrjuIc/hqdefault.jpg",
            "width": 480,
            "height": 360
          }
        },
        "channelTitle": "Super Simple Songs - Kids Songs",
        "liveBroadcastContent": "none",
        "publishTime": "2023-02-06T15:00:20Z"
      }
    },
    {
      "kind": "youtube#searchResult",
      "etag": "_7ck4DJhFbRCBEB3soKxfvpJCRg",
      "id": {
        "kind": "youtube#video",
        "videoId": "R8o-1mbEPFQ"
      },
      "snippet": {
        "publishedAt": "2023-02-02T15:00:16Z",
        "channelId": "UCLsooMJoIpl_7ux2jvdPB-Q",
        "title": "If You&#39;re Sleepy &amp; You Know It + More | 60 Minutes Of Children&#39;s Music | Super Simple Songs",
        "description": "Get the Super Simple App! ▻ http://bit.ly/TheSuperSimpleApp Enjoy an hour of kids songs that are perfect for a preschool dance ...",
        "thumbnails": {
          "default": {
            "url": "https://i.ytimg.com/vi/R8o-1mbEPFQ/default.jpg",
            "width": 120,
            "height": 90
          },
          "medium": {
            "url": "https://i.ytimg.com/vi/R8o-1mbEPFQ/mqdefault.jpg",
            "width": 320,
            "height": 180
          },
          "high": {
            "url": "https://i.ytimg.com/vi/R8o-1mbEPFQ/hqdefault.jpg",
            "width": 480,
            "height": 360
          }
        },
        "channelTitle": "Super Simple Songs - Kids Songs",
        "liveBroadcastContent": "none",
        "publishTime": "2023-02-02T15:00:16Z"
      }
    },
    {
      "kind": "youtube#searchResult",
      "etag": "GoiXCkG5C1n5rYMz05qopaQ5AuI",
      "id": {
        "kind": "youtube#video",
        "videoId": "N1L0IsANXTA"
      },
      "snippet": {
        "publishedAt": "2023-01-23T15:00:13Z",
        "channelId": "UCLsooMJoIpl_7ux2jvdPB-Q",
        "title": "As Quiet As A Mouse 🐭 #kidssongs #shorts #nurseryrhymes",
        "description": "Get the Super Simple App! ▻ http://bit.ly/TheSuperSimpleApp Learn some descriptive adjectives and animals in this super fun ...",
        "thumbnails": {
          "default": {
            "url": "https://i.ytimg.com/vi/N1L0IsANXTA/default.jpg",
            "width": 120,
            "height": 90
          },
          "medium": {
            "url": "https://i.ytimg.com/vi/N1L0IsANXTA/mqdefault.jpg",
            "width": 320,
            "height": 180
          },
          "high": {
            "url": "https://i.ytimg.com/vi/N1L0IsANXTA/hqdefault.jpg",
            "width": 480,
            "height": 360
          }
        },
        "channelTitle": "Super Simple Songs - Kids Songs",
        "liveBroadcastContent": "none",
        "publishTime": "2023-01-23T15:00:13Z"
      }
    },
    {
      "kind": "youtube#searchResult",
      "etag": "QX-XIYIzGDCbnTCBk-dmB4nmO9g",
      "id": {
        "kind": "youtube#video",
        "videoId": "DM6rMgkOSiE"
      },
      "snippet": {
        "publishedAt": "2023-01-21T15:00:15Z",
        "channelId": "UCLsooMJoIpl_7ux2jvdPB-Q",
        "title": "Hush Little Baby 😴 #shorts #supersimplesongs #lullaby",
        "description": "Get the Super Simple App! ▻ http://bit.ly/TheSuperSimpleApp Get ready for bed with this gentle lullaby for babies and toddlers.",
        "thumbnails": {
          "default": {
            "url": "https://i.ytimg.com/vi/DM6rMgkOSiE/default.jpg",
            "width": 120,
            "height": 90
          },
          "medium": {
            "url": "https://i.ytimg.com/vi/DM6rMgkOSiE/mqdefault.jpg",
            "width": 320,
            "height": 180
          },
          "high": {
            "url": "https://i.ytimg.com/vi/DM6rMgkOSiE/hqdefault.jpg",
            "width": 480,
            "height": 360
          }
        },
        "channelTitle": "Super Simple Songs - Kids Songs",
        "liveBroadcastContent": "none",
        "publishTime": "2023-01-21T15:00:15Z"
      }
    },
    {
      "kind": "youtube#searchResult",
      "etag": "5aGkUBlphswVTECVtnPMb51-ZAM",
      "id": {
        "kind": "youtube#video",
        "videoId": "GW84s5BglJU"
      },
      "snippet": {
        "publishedAt": "2023-01-19T15:00:16Z",
        "channelId": "UCLsooMJoIpl_7ux2jvdPB-Q",
        "title": "Nap Time + More | Kids Music Compilation | Super Simple Songs",
        "description": "Get the Super Simple App! ▻ http://bit.ly/TheSuperSimpleApp Get ready to relax and unwind with some Super Simple Songs.",
        "thumbnails": {
          "default": {
            "url": "https://i.ytimg.com/vi/GW84s5BglJU/default.jpg",
            "width": 120,
            "height": 90
          },
          "medium": {
            "url": "https://i.ytimg.com/vi/GW84s5BglJU/mqdefault.jpg",
            "width": 320,
            "height": 180
          },
          "high": {
            "url": "https://i.ytimg.com/vi/GW84s5BglJU/hqdefault.jpg",
            "width": 480,
            "height": 360
          }
        },
        "channelTitle": "Super Simple Songs - Kids Songs",
        "liveBroadcastContent": "none",
        "publishTime": "2023-01-19T15:00:16Z"
      }
    },
    {
      "kind": "youtube#searchResult",
      "etag": "3xbjQgI0UWHu8lo3Zj0UOgz7ltY",
      "id": {
        "kind": "youtube#video",
        "videoId": "PytrnxO_ONc"
      },
      "snippet": {
        "publishedAt": "2023-01-18T15:00:30Z",
        "channelId": "UCLsooMJoIpl_7ux2jvdPB-Q",
        "title": "Chinese Dragon Craft 🐉 #shorts #kidscrafts #lunarnewyear",
        "description": "Get the Super Simple App! ▻ http://bit.ly/TheSuperSimpleApp Celebrate Lunar New Year with a cool dragon craft!",
        "thumbnails": {
          "default": {
            "url": "https://i.ytimg.com/vi/PytrnxO_ONc/default.jpg",
            "width": 120,
            "height": 90
          },
          "medium": {
            "url": "https://i.ytimg.com/vi/PytrnxO_ONc/mqdefault.jpg",
            "width": 320,
            "height": 180
          },
          "high": {
            "url": "https://i.ytimg.com/vi/PytrnxO_ONc/hqdefault.jpg",
            "width": 480,
            "height": 360
          }
        },
        "channelTitle": "Super Simple Songs - Kids Songs",
        "liveBroadcastContent": "none",
        "publishTime": "2023-01-18T15:00:30Z"
      }
    },
    {
      "kind": "youtube#searchResult",
      "etag": "zP1I2_Z-2b8Z-3_YLJlZt7_6iEE",
      "id": {
        "kind": "youtube#video",
        "videoId": "YKuVcz-lfKE"
      },
      "snippet": {
        "publishedAt": "2023-01-14T15:00:29Z",
        "channelId": "UCLsooMJoIpl_7ux2jvdPB-Q",
        "title": "Clean Up! #shorts #supersimplesongs #cleanup",
        "description": "Get the Super Simple App! ▻ http://bit.ly/TheSuperSimpleApp Clean up, clean up. Everybody, let's clean up. Clean up, clean ...",
        "thumbnails": {
          "default": {
            "url": "https://i.ytimg.com/vi/YKuVcz-lfKE/default.jpg",
            "width": 120,
            "height": 90
          },
          "medium": {
            "url": "https://i.ytimg.com/vi/YKuVcz-lfKE/mqdefault.jpg",
            "width": 320,
            "height": 180
          },
          "high": {
            "url": "https://i.ytimg.com/vi/YKuVcz-lfKE/hqdefault.jpg",
            "width": 480,
            "height": 360
          }
        },
        "channelTitle": "Super Simple Songs - Kids Songs",
        "liveBroadcastContent": "none",
        "publishTime": "2023-01-14T15:00:29Z"
      }
    },
    {
      "kind": "youtube#searchResult",
      "etag": "tbUvpZ6PPvqvT4_iOYxdcW-E7Zw",
      "id": {
        "kind": "youtube#video",
        "videoId": "xZi81cbk41A"
      },
      "snippet": {
        "publishedAt": "2023-01-11T15:00:29Z",
        "channelId": "UCLsooMJoIpl_7ux2jvdPB-Q",
        "title": "Sun And Moon Craft  #shorts #kidscrafts #sunandmoon #supersimplecrafts",
        "description": "Get the Super Simple App! ▻ http://bit.ly/TheSuperSimpleApp Good morning and good night! Make a sun and moon paper ...",
        "thumbnails": {
          "default": {
            "url": "https://i.ytimg.com/vi/xZi81cbk41A/default.jpg",
            "width": 120,
            "height": 90
          },
          "medium": {
            "url": "https://i.ytimg.com/vi/xZi81cbk41A/mqdefault.jpg",
            "width": 320,
            "height": 180
          },
          "high": {
            "url": "https://i.ytimg.com/vi/xZi81cbk41A/hqdefault.jpg",
            "width": 480,
            "height": 360
          }
        },
        "channelTitle": "Super Simple Songs - Kids Songs",
        "liveBroadcastContent": "none",
        "publishTime": "2023-01-11T15:00:29Z"
      }
    },
    {
      "kind": "youtube#searchResult",
      "etag": "DTFEUI0voNhbJjLujivGjSdrqJU",
      "id": {
        "kind": "youtube#video",
        "videoId": "118nkULImiM"
      },
      "snippet": {
        "publishedAt": "2022-12-24T15:00:01Z",
        "channelId": "UCLsooMJoIpl_7ux2jvdPB-Q",
        "title": "Peekaboo Christmas #shorts #christmassongs",
        "description": "Get the Super Simple App! ▻ http://bit.ly/TheSuperSimpleApp Peekaboo! Peekaboo Cat is hiding. Can you find Peekaboo Cat ...",
        "thumbnails": {
          "default": {
            "url": "https://i.ytimg.com/vi/118nkULImiM/default.jpg",
            "width": 120,
            "height": 90
          },
          "medium": {
            "url": "https://i.ytimg.com/vi/118nkULImiM/mqdefault.jpg",
            "width": 320,
            "height": 180
          },
          "high": {
            "url": "https://i.ytimg.com/vi/118nkULImiM/hqdefault.jpg",
            "width": 480,
            "height": 360
          }
        },
        "channelTitle": "Super Simple Songs - Kids Songs",
        "liveBroadcastContent": "none",
        "publishTime": "2022-12-24T15:00:01Z"
      }
    },
    {
      "kind": "youtube#searchResult",
      "etag": "Ql47S9qYJ--2eAMB7MMX700CroE",
      "id": {
        "kind": "youtube#video",
        "videoId": "dEO-AlXFJl8"
      },
      "snippet": {
        "publishedAt": "2022-12-22T15:00:31Z",
        "channelId": "UCLsooMJoIpl_7ux2jvdPB-Q",
        "title": "Super Simple Christmas Songs | Kids Music | Family Holiday Carols",
        "description": "Get the Super Simple App! ▻ https://bit.ly/2W4dIsY Enjoy singing along to some festive songs of the season in the classroom and ...",
        "thumbnails": {
          "default": {
            "url": "https://i.ytimg.com/vi/dEO-AlXFJl8/default.jpg",
            "width": 120,
            "height": 90
          },
          "medium": {
            "url": "https://i.ytimg.com/vi/dEO-AlXFJl8/mqdefault.jpg",
            "width": 320,
            "height": 180
          },
          "high": {
            "url": "https://i.ytimg.com/vi/dEO-AlXFJl8/hqdefault.jpg",
            "width": 480,
            "height": 360
          }
        },
        "channelTitle": "Super Simple Songs - Kids Songs",
        "liveBroadcastContent": "none",
        "publishTime": "2022-12-22T15:00:31Z"
      }
    },
    {
      "kind": "youtube#searchResult",
      "etag": "IHyVk_7Y0HFUtdvQoHqW5W__b8o",
      "id": {
        "kind": "youtube#video",
        "videoId": "0m73sAV-I2c"
      },
      "snippet": {
        "publishedAt": "2022-09-29T14:00:00Z",
        "channelId": "UCLsooMJoIpl_7ux2jvdPB-Q",
        "title": "The Fish Go Swimming &amp; More Kids Songs | Super Simple Songs",
        "description": "Get the Super Simple App! ▻ http://bit.ly/TheSuperSimpleApp Sing and dance along to The Fish Go Swimming and more fun ...",
        "thumbnails": {
          "default": {
            "url": "https://i.ytimg.com/vi/0m73sAV-I2c/default.jpg",
            "width": 120,
            "height": 90
          },
          "medium": {
            "url": "https://i.ytimg.com/vi/0m73sAV-I2c/mqdefault.jpg",
            "width": 320,
            "height": 180
          },
          "high": {
            "url": "https://i.ytimg.com/vi/0m73sAV-I2c/hqdefault.jpg",
            "width": 480,
            "height": 360
          }
        },
        "channelTitle": "Super Simple Songs - Kids Songs",
        "liveBroadcastContent": "none",
        "publishTime": "2022-09-29T14:00:00Z"
      }
    },
    {
      "kind": "youtube#searchResult",
      "etag": "QTvkfSibWK5C0OKwuGhfJVcZqd8",
      "id": {
        "kind": "youtube#video",
        "videoId": "0MaL5XVmiwg"
      },
      "snippet": {
        "publishedAt": "2022-09-16T11:00:00Z",
        "channelId": "UCLsooMJoIpl_7ux2jvdPB-Q",
        "title": "There&#39;s a Monster In My Tummy #shorts #supersimplesongs #snacktime #kidssongs",
        "description": "Get the Super Simple App! ▻ http://bit.ly/TheSuperSimpleApp Uh-oh! Is your tummy grumbling? Maybe it's a hungry monster?",
        "thumbnails": {
          "default": {
            "url": "https://i.ytimg.com/vi/0MaL5XVmiwg/default.jpg",
            "width": 120,
            "height": 90
          },
          "medium": {
            "url": "https://i.ytimg.com/vi/0MaL5XVmiwg/mqdefault.jpg",
            "width": 320,
            "height": 180
          },
          "high": {
            "url": "https://i.ytimg.com/vi/0MaL5XVmiwg/hqdefault.jpg",
            "width": 480,
            "height": 360
          }
        },
        "channelTitle": "Super Simple Songs - Kids Songs",
        "liveBroadcastContent": "none",
        "publishTime": "2022-09-16T11:00:00Z"
      }
    },
    {
      "kind": "youtube#searchResult",
      "etag": "tlacPLFqvDv1QX-DWNyOfk40B5Y",
      "id": {
        "kind": "youtube#video",
        "videoId": "g9kiZ9wQIY0"
      },
      "snippet": {
        "publishedAt": "2022-09-11T14:15:01Z",
        "channelId": "UCLsooMJoIpl_7ux2jvdPB-Q",
        "title": "Pumpkin Spice Peekaboo! #shorts",
        "description": "Get the Super Simple App! ▻ http://bit.ly/TheSuperSimpleApp Here's a fun Peekaboo craft that you can do at home to celebrate ...",
        "thumbnails": {
          "default": {
            "url": "https://i.ytimg.com/vi/g9kiZ9wQIY0/default.jpg",
            "width": 120,
            "height": 90
          },
          "medium": {
            "url": "https://i.ytimg.com/vi/g9kiZ9wQIY0/mqdefault.jpg",
            "width": 320,
            "height": 180
          },
          "high": {
            "url": "https://i.ytimg.com/vi/g9kiZ9wQIY0/hqdefault.jpg",
            "width": 480,
            "height": 360
          }
        },
        "channelTitle": "Super Simple Songs - Kids Songs",
        "liveBroadcastContent": "none",
        "publishTime": "2022-09-11T14:15:01Z"
      }
    },
    {
      "kind": "youtube#searchResult",
      "etag": "hHALssVwQa1xkTvOfWAuX72sudU",
      "id": {
        "kind": "youtube#video",
        "videoId": "rgqIw8WoDps"
      },
      "snippet": {
        "publishedAt": "2022-09-10T14:35:00Z",
        "channelId": "UCLsooMJoIpl_7ux2jvdPB-Q",
        "title": "First We Wash Our Hands #shorts #handwash",
        "description": "Get the Super Simple App! ▻ http://bit.ly/TheSuperSimpleApp When it's time to eat, first we wash our hands. This song is super fun ...",
        "thumbnails": {
          "default": {
            "url": "https://i.ytimg.com/vi/rgqIw8WoDps/default.jpg",
            "width": 120,
            "height": 90
          },
          "medium": {
            "url": "https://i.ytimg.com/vi/rgqIw8WoDps/mqdefault.jpg",
            "width": 320,
            "height": 180
          },
          "high": {
            "url": "https://i.ytimg.com/vi/rgqIw8WoDps/hqdefault.jpg",
            "width": 480,
            "height": 360
          }
        },
        "channelTitle": "Super Simple Songs - Kids Songs",
        "liveBroadcastContent": "none",
        "publishTime": "2022-09-10T14:35:00Z"
      }
    },
    {
      "kind": "youtube#searchResult",
      "etag": "4sHnBBEWzb70v22ybwcSH-YnbFI",
      "id": {
        "kind": "youtube#video",
        "videoId": "G9mlcKj2HFA"
      },
      "snippet": {
        "publishedAt": "2022-07-07T14:00:13Z",
        "channelId": "UCLsooMJoIpl_7ux2jvdPB-Q",
        "title": "Mr. Golden Sun with Finny! &amp; More Finny the Shark Songs | Kids Songs | Super Simple Songs",
        "description": "Get the Super Simple App! ▻ http://bit.ly/TheSuperSimpleApp Let's sing Super Simple songs with Finny The Shark and friends ...",
        "thumbnails": {
          "default": {
            "url": "https://i.ytimg.com/vi/G9mlcKj2HFA/default.jpg",
            "width": 120,
            "height": 90
          },
          "medium": {
            "url": "https://i.ytimg.com/vi/G9mlcKj2HFA/mqdefault.jpg",
            "width": 320,
            "height": 180
          },
          "high": {
            "url": "https://i.ytimg.com/vi/G9mlcKj2HFA/hqdefault.jpg",
            "width": 480,
            "height": 360
          }
        },
        "channelTitle": "Super Simple Songs - Kids Songs",
        "liveBroadcastContent": "none",
        "publishTime": "2022-07-07T14:00:13Z"
      }
    },
    {
      "kind": "youtube#searchResult",
      "etag": "S4kd-jF80L2NOSJNzBR8F7pY4n4",
      "id": {
        "kind": "youtube#video",
        "videoId": "m-fXX-6DylU"
      },
      "snippet": {
        "publishedAt": "2022-06-23T14:00:32Z",
        "channelId": "UCLsooMJoIpl_7ux2jvdPB-Q",
        "title": "Super Simple Summertime Songs! | Kids Songs | Super Simple Songs",
        "description": "Get the Super Simple App! ▻ http://bit.ly/TheSuperSimpleApp Enjoy some Super Simple songs for summertime fun in the sun!",
        "thumbnails": {
          "default": {
            "url": "https://i.ytimg.com/vi/m-fXX-6DylU/default.jpg",
            "width": 120,
            "height": 90
          },
          "medium": {
            "url": "https://i.ytimg.com/vi/m-fXX-6DylU/mqdefault.jpg",
            "width": 320,
            "height": 180
          },
          "high": {
            "url": "https://i.ytimg.com/vi/m-fXX-6DylU/hqdefault.jpg",
            "width": 480,
            "height": 360
          }
        },
        "channelTitle": "Super Simple Songs - Kids Songs",
        "liveBroadcastContent": "none",
        "publishTime": "2022-06-23T14:00:32Z"
      }
    },
    {
      "kind": "youtube#searchResult",
      "etag": "kJZhnyNQfp4ZowD51cUlC-k6UpI",
      "id": {
        "kind": "youtube#video",
        "videoId": "oZa415bNvSA"
      },
      "snippet": {
        "publishedAt": "2022-06-16T14:00:19Z",
        "channelId": "UCLsooMJoIpl_7ux2jvdPB-Q",
        "title": "Peanut Butter &amp; Jelly featuring The Super Simple Puppets | Kids Songs | Super Simple Songs",
        "description": "Get the Super Simple App! ▻ http://bit.ly/TheSuperSimpleApp It's the Peanut Butter and Jelly song featuring the Super Simple ...",
        "thumbnails": {
          "default": {
            "url": "https://i.ytimg.com/vi/oZa415bNvSA/default.jpg",
            "width": 120,
            "height": 90
          },
          "medium": {
            "url": "https://i.ytimg.com/vi/oZa415bNvSA/mqdefault.jpg",
            "width": 320,
            "height": 180
          },
          "high": {
            "url": "https://i.ytimg.com/vi/oZa415bNvSA/hqdefault.jpg",
            "width": 480,
            "height": 360
          }
        },
        "channelTitle": "Super Simple Songs - Kids Songs",
        "liveBroadcastContent": "none",
        "publishTime": "2022-06-16T14:00:19Z"
      }
    },
    {
      "kind": "youtube#searchResult",
      "etag": "i4YKZMLkk_eEHaoYcTbZ1pXU-to",
      "id": {
        "kind": "youtube#video",
        "videoId": "kSNOF7vNplM"
      },
      "snippet": {
        "publishedAt": "2022-06-09T14:00:26Z",
        "channelId": "UCLsooMJoIpl_7ux2jvdPB-Q",
        "title": "There&#39;s A Monster In My Tummy | + More Kids Songs | Super Simple Songs",
        "description": "Get the Super Simple App! ▻ http://bit.ly/TheSuperSimpleApp Feed the monster in your tummy and stop the grumble, grumble, ...",
        "thumbnails": {
          "default": {
            "url": "https://i.ytimg.com/vi/kSNOF7vNplM/default.jpg",
            "width": 120,
            "height": 90
          },
          "medium": {
            "url": "https://i.ytimg.com/vi/kSNOF7vNplM/mqdefault.jpg",
            "width": 320,
            "height": 180
          },
          "high": {
            "url": "https://i.ytimg.com/vi/kSNOF7vNplM/hqdefault.jpg",
            "width": 480,
            "height": 360
          }
        },
        "channelTitle": "Super Simple Songs - Kids Songs",
        "liveBroadcastContent": "none",
        "publishTime": "2022-06-09T14:00:26Z"
      }
    },
    {
      "kind": "youtube#searchResult",
      "etag": "7VZOEpqGsqVkuto5rY-AkY5AQPk",
      "id": {
        "kind": "youtube#video",
        "videoId": "8VCpa4blanQ"
      },
      "snippet": {
        "publishedAt": "2022-05-19T14:00:05Z",
        "channelId": "UCLsooMJoIpl_7ux2jvdPB-Q",
        "title": "Five Little Speckled Frogs featuring The Super Simple Puppets | Kids Songs | Super Simple Songs",
        "description": "Get the Super Simple App! ▻ http://bit.ly/TheSuperSimpleApp Count down from five with this classic kids song as the frogs enjoy ...",
        "thumbnails": {
          "default": {
            "url": "https://i.ytimg.com/vi/8VCpa4blanQ/default.jpg",
            "width": 120,
            "height": 90
          },
          "medium": {
            "url": "https://i.ytimg.com/vi/8VCpa4blanQ/mqdefault.jpg",
            "width": 320,
            "height": 180
          },
          "high": {
            "url": "https://i.ytimg.com/vi/8VCpa4blanQ/hqdefault.jpg",
            "width": 480,
            "height": 360
          }
        },
        "channelTitle": "Super Simple Songs - Kids Songs",
        "liveBroadcastContent": "none",
        "publishTime": "2022-05-19T14:00:05Z"
      }
    },
    {
      "kind": "youtube#searchResult",
      "etag": "QgstqyeIqu_WM3YxR8cG3yOS_kE",
      "id": {
        "kind": "youtube#video",
        "videoId": "C_Sc5ZjdfFI"
      },
      "snippet": {
        "publishedAt": "2022-04-07T14:00:08Z",
        "channelId": "UCLsooMJoIpl_7ux2jvdPB-Q",
        "title": "The Seasons Song | Kids Songs | Super Simple Songs",
        "description": "Get the Super Simple App! ▻ http://bit.ly/TheSuperSimpleApp Let's celebrate all four seasons of the year while learning some ...",
        "thumbnails": {
          "default": {
            "url": "https://i.ytimg.com/vi/C_Sc5ZjdfFI/default.jpg",
            "width": 120,
            "height": 90
          },
          "medium": {
            "url": "https://i.ytimg.com/vi/C_Sc5ZjdfFI/mqdefault.jpg",
            "width": 320,
            "height": 180
          },
          "high": {
            "url": "https://i.ytimg.com/vi/C_Sc5ZjdfFI/hqdefault.jpg",
            "width": 480,
            "height": 360
          }
        },
        "channelTitle": "Super Simple Songs - Kids Songs",
        "liveBroadcastContent": "none",
        "publishTime": "2022-04-07T14:00:08Z"
      }
    },
    {
      "kind": "youtube#searchResult",
      "etag": "UGQj2g4VIb6a7zyEvYaLyxiG_3M",
      "id": {
        "kind": "youtube#video",
        "videoId": "_ify35SJcrI"
      },
      "snippet": {
        "publishedAt": "2022-03-31T13:00:30Z",
        "channelId": "UCLsooMJoIpl_7ux2jvdPB-Q",
        "title": "Healthy Habits! Kids Songs to Help Build Daily Routines from Super Simple Songs",
        "description": "Get the Super Simple App! ▻ http://bit.ly/TheSuperSimpleApp Building healthy habits is an important part of living a healthy life!",
        "thumbnails": {
          "default": {
            "url": "https://i.ytimg.com/vi/_ify35SJcrI/default.jpg",
            "width": 120,
            "height": 90
          },
          "medium": {
            "url": "https://i.ytimg.com/vi/_ify35SJcrI/mqdefault.jpg",
            "width": 320,
            "height": 180
          },
          "high": {
            "url": "https://i.ytimg.com/vi/_ify35SJcrI/hqdefault.jpg",
            "width": 480,
            "height": 360
          }
        },
        "channelTitle": "Super Simple Songs - Kids Songs",
        "liveBroadcastContent": "none",
        "publishTime": "2022-03-31T13:00:30Z"
      }
    },
    {
      "kind": "youtube#searchResult",
      "etag": "A41w2BbuN-um3zA1Ns1t0h7jye8",
      "id": {
        "kind": "youtube#video",
        "videoId": "9vg658ORVrc"
      },
      "snippet": {
        "publishedAt": "2022-01-27T15:00:53Z",
        "channelId": "UCLsooMJoIpl_7ux2jvdPB-Q",
        "title": "Here You Are, Thank You + More Songs for Kids | Super Simple Songs",
        "description": "Get the Super Simple App! ▻ http://bit.ly/TheSuperSimpleApp ------ Practice saying \"Thank you\" and \"You're welcome\" with ...",
        "thumbnails": {
          "default": {
            "url": "https://i.ytimg.com/vi/9vg658ORVrc/default.jpg",
            "width": 120,
            "height": 90
          },
          "medium": {
            "url": "https://i.ytimg.com/vi/9vg658ORVrc/mqdefault.jpg",
            "width": 320,
            "height": 180
          },
          "high": {
            "url": "https://i.ytimg.com/vi/9vg658ORVrc/hqdefault.jpg",
            "width": 480,
            "height": 360
          }
        },
        "channelTitle": "Super Simple Songs - Kids Songs",
        "liveBroadcastContent": "none",
        "publishTime": "2022-01-27T15:00:53Z"
      }
    },
    {
      "kind": "youtube#searchResult",
      "etag": "9UVn09i9eUws6FBImkf0X8NFf1M",
      "id": {
        "kind": "youtube#video",
        "videoId": "XorFEWPieMk"
      },
      "snippet": {
        "publishedAt": "2021-12-16T16:00:14Z",
        "channelId": "UCLsooMJoIpl_7ux2jvdPB-Q",
        "title": "Best of Super Simple Songs 2021 | Kids Songs | Super Simple Songs",
        "description": "Get the Super Simple App! ▻ http://bit.ly/TheSuperSimpleApp Enjoy this collection of the best new songs of 2021 from Super ...",
        "thumbnails": {
          "default": {
            "url": "https://i.ytimg.com/vi/XorFEWPieMk/default.jpg",
            "width": 120,
            "height": 90
          },
          "medium": {
            "url": "https://i.ytimg.com/vi/XorFEWPieMk/mqdefault.jpg",
            "width": 320,
            "height": 180
          },
          "high": {
            "url": "https://i.ytimg.com/vi/XorFEWPieMk/hqdefault.jpg",
            "width": 480,
            "height": 360
          }
        },
        "channelTitle": "Super Simple Songs - Kids Songs",
        "liveBroadcastContent": "none",
        "publishTime": "2021-12-16T16:00:14Z"
      }
    },
    {
      "kind": "youtube#searchResult",
      "etag": "3LdQqriF4IkeRxU5oabbEbjLJaA",
      "id": {
        "kind": "youtube#video",
        "videoId": "9iLcWuxZlQ4"
      },
      "snippet": {
        "publishedAt": "2021-12-02T16:00:03Z",
        "channelId": "UCLsooMJoIpl_7ux2jvdPB-Q",
        "title": "Milk &amp; Cookies + More Christmas Songs for Kids",
        "description": "Get the Super Simple App! ▻ http://bit.ly/TheSuperSimpleApp Celebrate the holiday season with Super Simple Songs and this ...",
        "thumbnails": {
          "default": {
            "url": "https://i.ytimg.com/vi/9iLcWuxZlQ4/default.jpg",
            "width": 120,
            "height": 90
          },
          "medium": {
            "url": "https://i.ytimg.com/vi/9iLcWuxZlQ4/mqdefault.jpg",
            "width": 320,
            "height": 180
          },
          "high": {
            "url": "https://i.ytimg.com/vi/9iLcWuxZlQ4/hqdefault.jpg",
            "width": 480,
            "height": 360
          }
        },
        "channelTitle": "Super Simple Songs - Kids Songs",
        "liveBroadcastContent": "none",
        "publishTime": "2021-12-02T16:00:03Z"
      }
    },
    {
      "kind": "youtube#searchResult",
      "etag": "c407x1avhzkyVmi4I8xaBvUMiyY",
      "id": {
        "kind": "youtube#video",
        "videoId": "y0G6yTVCs3s"
      },
      "snippet": {
        "publishedAt": "2021-10-21T14:15:04Z",
        "channelId": "UCLsooMJoIpl_7ux2jvdPB-Q",
        "title": "Let&#39;s Decorate The House For Halloween + More Kids Songs",
        "description": "Get the Super Simple App! ▻ http://bit.ly/TheSuperSimpleApp Enjoy this collection of Halloween songs for kids from Super Simple ...",
        "thumbnails": {
          "default": {
            "url": "https://i.ytimg.com/vi/y0G6yTVCs3s/default.jpg",
            "width": 120,
            "height": 90
          },
          "medium": {
            "url": "https://i.ytimg.com/vi/y0G6yTVCs3s/mqdefault.jpg",
            "width": 320,
            "height": 180
          },
          "high": {
            "url": "https://i.ytimg.com/vi/y0G6yTVCs3s/hqdefault.jpg",
            "width": 480,
            "height": 360
          }
        },
        "channelTitle": "Super Simple Songs - Kids Songs",
        "liveBroadcastContent": "none",
        "publishTime": "2021-10-21T14:15:04Z"
      }
    },
    {
      "kind": "youtube#searchResult",
      "etag": "2XXNn12a27YO_SBLzCKr57unRHU",
      "id": {
        "kind": "youtube#video",
        "videoId": "im8in5pIqqM"
      },
      "snippet": {
        "publishedAt": "2021-10-07T10:30:05Z",
        "channelId": "UCLsooMJoIpl_7ux2jvdPB-Q",
        "title": "Let&#39;s Decorate The House For Halloween | Super Simple Songs",
        "description": "Get the Super Simple App! ▻ http://bit.ly/TheSuperSimpleApp It's time to decorate the house for Halloween with ghosts, ...",
        "thumbnails": {
          "default": {
            "url": "https://i.ytimg.com/vi/im8in5pIqqM/default.jpg",
            "width": 120,
            "height": 90
          },
          "medium": {
            "url": "https://i.ytimg.com/vi/im8in5pIqqM/mqdefault.jpg",
            "width": 320,
            "height": 180
          },
          "high": {
            "url": "https://i.ytimg.com/vi/im8in5pIqqM/hqdefault.jpg",
            "width": 480,
            "height": 360
          }
        },
        "channelTitle": "Super Simple Songs - Kids Songs",
        "liveBroadcastContent": "none",
        "publishTime": "2021-10-07T10:30:05Z"
      }
    }
  ]
}
