{
  "kind": "youtube#searchListResponse",
  "etag": "aBspUdsgqM9ElJdWUaiy_D8KhaI",
  "regionCode": "US",
  "pageInfo": {
    "totalResults": 15,
    "resultsPerPage": 15
  },
  "items": [
    {
      "kind": "youtube#searchResult",
      "etag": "Fmu4HPN5HUkhE_Vtk0ZrTCHXpdc",
      "id": {
        "kind": "youtube#video",
        "videoId": "iqVqhkIqfuk"
      },
      "snippet": {
        "publishedAt": "2025-09-11T00:01:00Z",
        "channelId": "UCAJ41d46i6mcNAsvsWRc9hw",
        "title": "Minecraft: Reclamation Ep. 16 - Hidden Realm",
        "description": "In Reclamation we must try to make nice greenery in a barren wasteland and save the world Thanks to Apex Hosting for ...",
        "thumbnails": {
          "default": {
            "url": "https://i.ytimg.com/vi/iqVqhkIqfuk/default.jpg",
            "width": 120,
            "height": 90
          },
          "medium": {
            "url": "https://i.ytimg.com/vi/iqVqhkIqfuk/mqdefault.jpg",
            "width": 320,
            "height": 180
          },
          "high": {
            "url": "https://i.ytimg.com/vi/iqVqhkIqfuk/hqdefault.jpg",
            "width": 480,
            "height": 360
          }
        },
        "channelTitle": "CaptainSparklez 2",
        "liveBroadcastContent": "none",
        "publishTime": "2025-09-11T00:01:00Z"
      }
    },
    {
      "kind": "youtube#searchResult",
      "etag": "lxnj2-X5uOOrEJ65bbktLVHVqqg",
      "id": {
        "kind": "youtube#video",
        "videoId": "csGHzb4wKTw"
      },
      "snippet": {
        "publishedAt": "2025-09-10T17:00:57Z",
        "channelId": "UCAJ41d46i6mcNAsvsWRc9hw",
        "title": "Minecraft.A.I.M",
        "description": "I have no idea why this is called Maim but it's a pretty cool time Thanks to Apex Hosting for sponsoring this video! Use code ...",
        "thumbnails": {
          "default": {
            "url": "https://i.ytimg.com/vi/csGHzb4wKTw/default.jpg",
            "width": 120,
            "height": 90
          },
          "medium": {
            "url": "https://i.ytimg.com/vi/csGHzb4wKTw/mqdefault.jpg",
            "width": 320,
            "height": 180
          },
          "high": {
            "url": "https://i.ytimg.com/vi/csGHzb4wKTw/hqdefault.jpg",
            "width": 480,
            "height": 360
          }
        },
        "channelTitle": "CaptainSparklez 2",
        "liveBroadcastContent": "none",
        "publishTime": "2025-09-10T17:00:57Z"
      }
    },
    {
      "kind": "youtube#searchResult",
      "etag": "EfwHBn5vFTSwubO20RZ2gPvwPp4",
      "id": {
        "kind": "youtube#video",
        "videoId": "F1Friges6Qg"
      },
      "snippet": {
        "publishedAt": "2025-09-10T12:00:33Z",
        "channelId": "UCAJ41d46i6mcNAsvsWRc9hw",
        "title": "15 year Minecraft player btw",
        "description": "Full vod: https://www.youtube.com/watch?v=g3IoPVlGl1I #shorts #minecraft #funny.",
        "thumbnails": {
          "default": {
            "url": "https://i.ytimg.com/vi/F1Friges6Qg/default.jpg",
            "width": 120,
            "height": 90
          },
          "medium": {
            "url": "https://i.ytimg.com/vi/F1Friges6Qg/mqdefault.jpg",
            "width": 320,
            "height": 180
          },
          "high": {
            "url": "https://i.ytimg.com/vi/F1Friges6Qg/hqdefault.jpg",
            "width": 480,
            "height": 360
          }
        },
        "channelTitle": "CaptainSparklez 2",
        "liveBroadcastContent": "none",
        "publishTime": "2025-09-10T12:00:33Z"
      }
    },
    {
      "kind": "youtube#searchResult",
      "etag": "qRo-qOzfJVHOcrqwihFpov41j-s",
      "id": {
        "kind": "youtube#video",
        "videoId": "IeTf5CnUjS8"
      },
      "snippet": {
        "publishedAt": "2025-09-10T00:00:32Z",
        "channelId": "UCAJ41d46i6mcNAsvsWRc9hw",
        "title": "Minecraft: Liminal Industries Ep. 19",
        "description": "We are stuck in the backrooms and must forge the eyes to escape Thanks to Apex Hosting for sponsoring this series! Use code ...",
        "thumbnails": {
          "default": {
            "url": "https://i.ytimg.com/vi/IeTf5CnUjS8/default.jpg",
            "width": 120,
            "height": 90
          },
          "medium": {
            "url": "https://i.ytimg.com/vi/IeTf5CnUjS8/mqdefault.jpg",
            "width": 320,
            "height": 180
          },
          "high": {
            "url": "https://i.ytimg.com/vi/IeTf5CnUjS8/hqdefault.jpg",
            "width": 480,
            "height": 360
          }
        },
        "channelTitle": "CaptainSparklez 2",
        "liveBroadcastContent": "none",
        "publishTime": "2025-09-10T00:00:32Z"
      }
    },
    {
      "kind": "youtube#searchResult",
      "etag": "HGpI89jjAYUvJgs_24_FeEQ2ZAs",
      "id": {
        "kind": "youtube#video",
        "videoId": "4PXroSZx64k"
      },
      "snippet": {
        "publishedAt": "2025-09-09T17:00:06Z",
        "channelId": "UCAJ41d46i6mcNAsvsWRc9hw",
        "title": "Cobblemon Academy Ep. 5 - Legendary Gyms",
        "description": "Cobblemon Academy is a Minecraft SMP where we must catch Pokemon, join a house, and be the best. Thanks to Apex Hosting ...",
        "thumbnails": {
          "default": {
            "url": "https://i.ytimg.com/vi/4PXroSZx64k/default.jpg",
            "width": 120,
            "height": 90
          },
          "medium": {
            "url": "https://i.ytimg.com/vi/4PXroSZx64k/mqdefault.jpg",
            "width": 320,
            "height": 180
          },
          "high": {
            "url": "https://i.ytimg.com/vi/4PXroSZx64k/hqdefault.jpg",
            "width": 480,
            "height": 360
          }
        },
        "channelTitle": "CaptainSparklez 2",
        "liveBroadcastContent": "none",
        "publishTime": "2025-09-09T17:00:06Z"
      }
    },
    {
      "kind": "youtube#searchResult",
      "etag": "mJrcScLflz3vMQw3u3Vw8jurx5Y",
      "id": {
        "kind": "youtube#video",
        "videoId": "0xLUaEy-2rQ"
      },
      "snippet": {
        "publishedAt": "2025-09-09T00:00:01Z",
        "channelId": "UCAJ41d46i6mcNAsvsWRc9hw",
        "title": "Abandoned On The Way To The PEAK",
        "description": "Today we try ascent 6 again and the herd thins PEAK Playlist: ...",
        "thumbnails": {
          "default": {
            "url": "https://i.ytimg.com/vi/0xLUaEy-2rQ/default.jpg",
            "width": 120,
            "height": 90
          },
          "medium": {
            "url": "https://i.ytimg.com/vi/0xLUaEy-2rQ/mqdefault.jpg",
            "width": 320,
            "height": 180
          },
          "high": {
            "url": "https://i.ytimg.com/vi/0xLUaEy-2rQ/hqdefault.jpg",
            "width": 480,
            "height": 360
          }
        },
        "channelTitle": "CaptainSparklez 2",
        "liveBroadcastContent": "none",
        "publishTime": "2025-09-09T00:00:01Z"
      }
    },
    {
      "kind": "youtube#searchResult",
      "etag": "PyjJu4vd2wfrPeLWlMGArnTJ--w",
      "id": {
        "kind": "youtube#video",
        "videoId": "nkNjTUHGrE4"
      },
      "snippet": {
        "publishedAt": "2025-09-08T17:01:06Z",
        "channelId": "UCAJ41d46i6mcNAsvsWRc9hw",
        "title": "Minecraft: Reclamation Ep. 15 - Crushing Loaf",
        "description": "In Reclamation we must try to make nice greenery in a barren wasteland and save the world Thanks to Apex Hosting for ...",
        "thumbnails": {
          "default": {
            "url": "https://i.ytimg.com/vi/nkNjTUHGrE4/default.jpg",
            "width": 120,
            "height": 90
          },
          "medium": {
            "url": "https://i.ytimg.com/vi/nkNjTUHGrE4/mqdefault.jpg",
            "width": 320,
            "height": 180
          },
          "high": {
            "url": "https://i.ytimg.com/vi/nkNjTUHGrE4/hqdefault.jpg",
            "width": 480,
            "height": 360
          }
        },
        "channelTitle": "CaptainSparklez 2",
        "liveBroadcastContent": "none",
        "publishTime": "2025-09-08T17:01:06Z"
      }
    },
    {
      "kind": "youtube#searchResult",
      "etag": "vdOnoj_la-OVeB-MiXO-HQDOGMQ",
      "id": {
        "kind": "youtube#video",
        "videoId": "AqoUzuSai_4"
      },
      "snippet": {
        "publishedAt": "2025-09-08T00:00:11Z",
        "channelId": "UCAJ41d46i6mcNAsvsWRc9hw",
        "title": "Mildly Bad Drivers #7",
        "description": "Some people have no survival instincts Idiots In Cars playlist: ...",
        "thumbnails": {
          "default": {
            "url": "https://i.ytimg.com/vi/AqoUzuSai_4/default.jpg",
            "width": 120,
            "height": 90
          },
          "medium": {
            "url": "https://i.ytimg.com/vi/AqoUzuSai_4/mqdefault.jpg",
            "width": 320,
            "height": 180
          },
          "high": {
            "url": "https://i.ytimg.com/vi/AqoUzuSai_4/hqdefault.jpg",
            "width": 480,
            "height": 360
          }
        },
        "channelTitle": "CaptainSparklez 2",
        "liveBroadcastContent": "none",
        "publishTime": "2025-09-08T00:00:11Z"
      }
    },
    {
      "kind": "youtube#searchResult",
      "etag": "xIaAAv9acnAuiQZD5z0cMV00xKc",
      "id": {
        "kind": "youtube#video",
        "videoId": "ywPAxstyI0k"
      },
      "snippet": {
        "publishedAt": "2025-09-07T17:01:22Z",
        "channelId": "UCAJ41d46i6mcNAsvsWRc9hw",
        "title": "Cobblemon Academy Ep. 4 - RIP Server",
        "description": "Cobblemon Academy is a Minecraft SMP where we must catch Pokemon, join a house, and be the best. Thanks to Apex Hosting ...",
        "thumbnails": {
          "default": {
            "url": "https://i.ytimg.com/vi/ywPAxstyI0k/default.jpg",
            "width": 120,
            "height": 90
          },
          "medium": {
            "url": "https://i.ytimg.com/vi/ywPAxstyI0k/mqdefault.jpg",
            "width": 320,
            "height": 180
          },
          "high": {
            "url": "https://i.ytimg.com/vi/ywPAxstyI0k/hqdefault.jpg",
            "width": 480,
            "height": 360
          }
        },
        "channelTitle": "CaptainSparklez 2",
        "liveBroadcastContent": "none",
        "publishTime": "2025-09-07T17:01:22Z"
      }
    },
    {
      "kind": "youtube#searchResult",
      "etag": "_txuqU8nrRjpt7_Bc89YkD1Lwco",
      "id": {
        "kind": "youtube#video",
        "videoId": "K_QjtvvSYr4"
      },
      "snippet": {
        "publishedAt": "2025-09-06T17:00:25Z",
        "channelId": "UCAJ41d46i6mcNAsvsWRc9hw",
        "title": "Minecraft: Liminal Industries Ep. 18",
        "description": "We are stuck in the backrooms and must forge the eyes to escape Thanks to Apex Hosting for sponsoring this series! Use code ...",
        "thumbnails": {
          "default": {
            "url": "https://i.ytimg.com/vi/K_QjtvvSYr4/default.jpg",
            "width": 120,
            "height": 90
          },
          "medium": {
            "url": "https://i.ytimg.com/vi/K_QjtvvSYr4/mqdefault.jpg",
            "width": 320,
            "height": 180
          },
          "high": {
            "url": "https://i.ytimg.com/vi/K_QjtvvSYr4/hqdefault.jpg",
            "width": 480,
            "height": 360
          }
        },
        "channelTitle": "CaptainSparklez 2",
        "liveBroadcastContent": "none",
        "publishTime": "2025-09-06T17:00:25Z"
      }
    },
    {
      "kind": "youtube#searchResult",
      "etag": "VYHdG37T78hhPK2uzsNo6Hcn0N0",
      "id": {
        "kind": "youtube#video",
        "videoId": "M-VzgtEzVTU"
      },
      "snippet": {
        "publishedAt": "2025-09-06T12:00:44Z",
        "channelId": "UCAJ41d46i6mcNAsvsWRc9hw",
        "title": "Swear word purgatory",
        "description": "Full vod: Was only on twitch #shorts #peak #funny.",
        "thumbnails": {
          "default": {
            "url": "https://i.ytimg.com/vi/M-VzgtEzVTU/default.jpg",
            "width": 120,
            "height": 90
          },
          "medium": {
            "url": "https://i.ytimg.com/vi/M-VzgtEzVTU/mqdefault.jpg",
            "width": 320,
            "height": 180
          },
          "high": {
            "url": "https://i.ytimg.com/vi/M-VzgtEzVTU/hqdefault.jpg",
            "width": 480,
            "height": 360
          }
        },
        "channelTitle": "CaptainSparklez 2",
        "liveBroadcastContent": "none",
        "publishTime": "2025-09-06T12:00:44Z"
      }
    },
    {
      "kind": "youtube#searchResult",
      "etag": "MfOx5qbvZN23dE65goPv1e-GFV0",
      "id": {
        "kind": "youtube#video",
        "videoId": "fugWVZz9iRA"
      },
      "snippet": {
        "publishedAt": "2025-09-06T00:01:00Z",
        "channelId": "UCAJ41d46i6mcNAsvsWRc9hw",
        "title": "Minecraft: Reclamation Ep. 14 - Magic",
        "description": "In Reclamation we must try to make nice greenery in a barren wasteland and save the world Thanks to Apex Hosting for ...",
        "thumbnails": {
          "default": {
            "url": "https://i.ytimg.com/vi/fugWVZz9iRA/default.jpg",
            "width": 120,
            "height": 90
          },
          "medium": {
            "url": "https://i.ytimg.com/vi/fugWVZz9iRA/mqdefault.jpg",
            "width": 320,
            "height": 180
          },
          "high": {
            "url": "https://i.ytimg.com/vi/fugWVZz9iRA/hqdefault.jpg",
            "width": 480,
            "height": 360
          }
        },
        "channelTitle": "CaptainSparklez 2",
        "liveBroadcastContent": "none",
        "publishTime": "2025-09-06T00:01:00Z"
      }
    },
    {
      "kind": "youtube#searchResult",
      "etag": "24H0nuzJajrQbjDYMwuqzfABRDY",
      "id": {
        "kind": "youtube#video",
        "videoId": "sNc35jJLnQw"
      },
      "snippet": {
        "publishedAt": "2025-09-05T17:01:16Z",
        "channelId": "UCAJ41d46i6mcNAsvsWRc9hw",
        "title": "Cobblemon Academy Ep. 3 - A New Home",
        "description": "Cobblemon Academy is a Minecraft SMP where we must catch Pokemon, join a house, and be the best. Thanks to Apex Hosting ...",
        "thumbnails": {
          "default": {
            "url": "https://i.ytimg.com/vi/sNc35jJLnQw/default.jpg",
            "width": 120,
            "height": 90
          },
          "medium": {
            "url": "https://i.ytimg.com/vi/sNc35jJLnQw/mqdefault.jpg",
            "width": 320,
            "height": 180
          },
          "high": {
            "url": "https://i.ytimg.com/vi/sNc35jJLnQw/hqdefault.jpg",
            "width": 480,
            "height": 360
          }
        },
        "channelTitle": "CaptainSparklez 2",
        "liveBroadcastContent": "none",
        "publishTime": "2025-09-05T17:01:16Z"
      }
    },
    {
      "kind": "youtube#searchResult",
      "etag": "8StLxaXrcLNBNVMfPguvkdRUnYE",
      "id": {
        "kind": "youtube#video",
        "videoId": "LkLG1ZKyQw8"
      },
      "snippet": {
        "publishedAt": "2025-09-04T00:00:25Z",
        "channelId": "UCAJ41d46i6mcNAsvsWRc9hw",
        "title": "Cobblemon Academy Ep. 2 - Gimme Gold",
        "description": "Cobblemon Academy is a Minecraft SMP where we must catch Pokemon, join a house, and be the best. Thanks to Apex Hosting ...",
        "thumbnails": {
          "default": {
            "url": "https://i.ytimg.com/vi/LkLG1ZKyQw8/default.jpg",
            "width": 120,
            "height": 90
          },
          "medium": {
            "url": "https://i.ytimg.com/vi/LkLG1ZKyQw8/mqdefault.jpg",
            "width": 320,
            "height": 180
          },
          "high": {
            "url": "https://i.ytimg.com/vi/LkLG1ZKyQw8/hqdefault.jpg",
            "width": 480,
            "height": 360
          }
        },
        "channelTitle": "CaptainSparklez 2",
        "liveBroadcastContent": "none",
        "publishTime": "2025-09-04T00:00:25Z"
      }
    },
    {
      "kind": "youtube#searchResult",
      "etag": "CbKMJz2r6IHP59KqMDeh4G_msxU",
      "id": {
        "kind": "youtube#video",
        "videoId": "k0XYMHUkkIU"
      },
      "snippet": {
        "publishedAt": "2025-09-02T17:00:59Z",
        "channelId": "UCAJ41d46i6mcNAsvsWRc9hw",
        "title": "Cobblemon Academy Ep. 1 - A New Beginning",
        "description": "Cobblemon Academy is a Minecraft SMP where we must catch Pokemon, join a house, and be the best. Thanks to Apex Hosting ...",
        "thumbnails": {
          "default": {
            "url": "https://i.ytimg.com/vi/k0XYMHUkkIU/default.jpg",
            "width": 120,
            "height": 90
          },
          "medium": {
            "url": "https://i.ytimg.com/vi/k0XYMHUkkIU/mqdefault.jpg",
            "width": 320,
            "height": 180
          },
          "high": {
            "url": "https://i.ytimg.com/vi/k0XYMHUkkIU/hqdefault.jpg",
            "width": 480,
            "height": 360
          }
        },
        "channelTitle": "CaptainSparklez 2",
        "liveBroadcastContent": "none",
        "publishTime": "2025-09-02T17:00:59Z"
      }
    }
  ]
}
